redshiftsql/__init__.py
redshiftsql/__main__.py
redshiftsql-0.0.7.dist-info/DESCRIPTION.rst
redshiftsql-0.0.7.dist-info/METADATA
redshiftsql-0.0.7.dist-info/RECORD
redshiftsql-0.0.7.dist-info/WHEEL
redshiftsql-0.0.7.dist-info/metadata.json
redshiftsql-0.0.7.dist-info/top_level.txt
