Metadata-Version: 2.0
Name: redshiftsql
Version: 0.0.7
Summary: Executes SQL commands from STDIN in a single transaction
Home-page: https://github.com/QuiNovas/redshiftsql
Author: Joseph Wortmann
Author-email: joseph.wortmann@gmail.com
License: APL 2.0
Keywords: quinovas
Platform: UNKNOWN
Classifier: Development Status :: 3 - Alpha
Classifier: Topic :: System :: Software Distribution
Classifier: Intended Audience :: Developers
Classifier: License :: OSI Approved :: Apache Software License
Classifier: Programming Language :: Python :: 2.7
Requires-Dist: argparse
Requires-Dist: boto3
Requires-Dist: psycopg2-binary
